drummachine/__init__.py
drummachine/__main__.py
drummachine/samples.py
drummachine/waveforms.py
drummachine-0.4.5.dist-info/METADATA
drummachine-0.4.5.dist-info/WHEEL
drummachine-0.4.5.dist-info/licenses/LICENSE
drummachine-0.4.5.dist-info/RECORD
