Metadata-Version: 2.1
Name: drummachine
Version: 0.4.5
Summary: A drum machine package for sequencing waveforms using numpy, curses and the sounddevice module.
Project-URL: Homepage, https://github.com/guitardan/realtime-audio
Project-URL: Bug Tracker, https://github.com/guitardan/realtime-audio/issues
Author-email: Guitar Dan <guitardanuk@gmail.com>
License-File: LICENSE
Keywords: audio,drums,music
Classifier: Environment :: Console :: Curses
Classifier: License :: OSI Approved :: MIT License
Classifier: Operating System :: MacOS
Classifier: Programming Language :: Python :: 3
Classifier: Topic :: Multimedia :: Sound/Audio :: Sound Synthesis
Requires-Python: >=3.8
Requires-Dist: numpy
Requires-Dist: sounddevice
Requires-Dist: soundfile
Requires-Dist: windows-curses; platform_system == 'Windows'
